{
  "version": "0.1.0",
  "build": 1,
  "date": "2026-06-19",
  "title": "מהדורה ראשונה",
  "notes": [
    "מציג PDF ממוקד-מקלדת עם פלטת פקודות (Ctrl+Shift+P) שמגיעה לכל פעולה",
    "כלי עמוד: החלפה, מחיקה, סיבוב, הזזה, הוספה, חילוץ ומיזוג תיקייה שלמה לקובץ PDF אחד",
    "מצב עריכה: הוספה ועיצוב של שדות טקסט ושכבות-על של תמונות, ולאחר מכן ייצוא שלהן אל המסמך",
    "חיפוש גם בטקסט העמוד וגם בשדות טופס, עם הדגשה",
    "זום עם רינדור חד, אחוז זום בזמן אמת וברירות מחדל שנשמרות לכל מסמך",
    "הדפסת מסמכים ושינוי שיוך של כל קיצור מקלדת לפי טעמך",
    "מסך \"מה חדש\" כדי שתוכל/י להתעדכן בשינויים בכל עת",
    "כל פעולה בעמוד יוצרת תחילה גיבוי עם חותמת זמן, כך שהמקור שלך בטוח"
  ]
}